LICENSE
README.md
setup.py
SmartDataKit/__init__.py
SmartDataKit.egg-info/PKG-INFO
SmartDataKit.egg-info/SOURCES.txt
SmartDataKit.egg-info/dependency_links.txt
SmartDataKit.egg-info/requires.txt
SmartDataKit.egg-info/top_level.txt
SmartDataKit/Exception/__init__.py
SmartDataKit/analyze_src/BasicDataInspection.py
SmartDataKit/analyze_src/__init__.py
SmartDataKit/analyze_src/univariante_analysis.py
SmartDataKit/base/__init__.py
SmartDataKit/base/base.py
SmartDataKit/impute/Skimputer.py
SmartDataKit/impute/__init__.py
SmartDataKit/impute/pandimputer.py
SmartDataKit/logger/__init__.py