Metadata-Version: 2.2
Name: SmartDataKit
Version: 0.3.1
Author: Vishnu
Author-email: vishnurrajeev@gmail.com
License-File: LICENSE
Requires-Dist: pandas
Requires-Dist: numpy
Requires-Dist: seaborn
Requires-Dist: matplotlib
Requires-Dist: scikit-learn
Dynamic: author
Dynamic: author-email
Dynamic: requires-dist
